echofish_aws_indexing_lambda/__init__.py
echofish_aws_indexing_lambda/lambda_executor.py
echofish_aws_indexing_lambda/lambda_handler.py
echofish_aws_indexing_lambda-1.0.0.dist-info/LICENSE
echofish_aws_indexing_lambda-1.0.0.dist-info/METADATA
echofish_aws_indexing_lambda-1.0.0.dist-info/WHEEL
echofish_aws_indexing_lambda-1.0.0.dist-info/top_level.txt
echofish_aws_indexing_lambda-1.0.0.dist-info/RECORD
