Metadata-Version: 2.1
Name: echofish-aws-indexing-lambda
Version: 1.0.0
Home-page: https://github.com/ci-cmg/echofish-aws-indexing-lambda
Classifier: Programming Language :: Python :: 3.9
Classifier: License :: OSI Approved :: MIT License
Requires-Python: >=3.9
License-File: LICENSE
Requires-Dist: pandas ==1.5.3
Requires-Dist: numpy ==1.23.4
Requires-Dist: boto3 ==1.26.76
Requires-Dist: botocore ==1.29.76
